main.py
glass_onion-0.0.1.dist-info/METADATA
glass_onion-0.0.1.dist-info/WHEEL
glass_onion-0.0.1.dist-info/top_level.txt
glass_onion-0.0.1.dist-info/RECORD
