Metadata-Version: 2.4
Name: glass_onion
Version: 0.0.1
Summary: TBA.
Requires-Python: >=3.11
